PyPriroda/.DS_Store
PyPriroda/CreateFiles.py
PyPriroda/__init__.py
pypriroda-1.0.1.dist-info/METADATA
pypriroda-1.0.1.dist-info/WHEEL
pypriroda-1.0.1.dist-info/licenses/LICENSE
pypriroda-1.0.1.dist-info/RECORD
