Metadata-Version: 2.1
Name: PyPriroda
Version: 1.0.1
Summary: A library for quantum calculations
Project-URL: Homepage, https://github.com/besthedgehog/PyPriroda
Project-URL: Bug Tracker, https://github.com/besthedgehog/PyPriroda/issues
Author-email: Alexey Polukhin <alexpolukin@yandex.ru>
License-File: LICENSE
Classifier: License :: OSI Approved :: MIT License
Classifier: Operating System :: OS Independent
Classifier: Programming Language :: Python :: 3
Requires-Python: >=3.7
